textmark/TextAnnotation.py
textmark/Visualizer.py
textmark/__init__.py
textmark/tools.py
textmark-0.5.0.dist-info/LICENSE
textmark-0.5.0.dist-info/METADATA
textmark-0.5.0.dist-info/WHEEL
textmark-0.5.0.dist-info/top_level.txt
textmark-0.5.0.dist-info/RECORD
