Metadata-Version: 2.1
Name: textmark
Version: 0.5.0
Summary: Text annotation utilities for computer vision pipelines.
Author-email: David Jones <d.t.jones@outlook.com>
Maintainer-email: David Jones <d.t.jones@outlook.com>
License: Copyright (c) 2024 David Jones
Project-URL: homepage, https://github.com/davidtjones/textmark
Project-URL: repository, https://github.com/davidtjones/textmark
Keywords: text,annotation,vision
License-File: LICENSE
Requires-Dist: numpy >=1.19.0
Requires-Dist: Pillow >10.0.0
Requires-Dist: requests >=2.31.0
Requires-Dist: shapely >2.0.0
